ultrafastrss/__about__.py
ultrafastrss/__init__.py
ultrafastrss/ultrafastrss.py
ultrafastrss-0.9.3.dist-info/METADATA
ultrafastrss-0.9.3.dist-info/WHEEL
ultrafastrss-0.9.3.dist-info/licenses/LICENSE.txt
ultrafastrss-0.9.3.dist-info/RECORD
