Metadata-Version: 2.4
Name: ultrafastrss
Version: 0.9.3
Summary: Async Simple and fast RSS parser module.
Project-URL: Documentation, https://github.com/nocomplexity/ultrafastrss#readme
Project-URL: Issues, https://github.com/nocomplexity/ultrafastrss/issues
Project-URL: Source, https://github.com/nocomplexity/ultrafastrss
Author-email: Maikel Mardjan <mike@bm-support.org>
License-Expression: GPL-3.0-or-later
License-File: LICENSE.txt
Classifier: Development Status :: 4 - Beta
Classifier: Programming Language :: Python
Classifier: Programming Language :: Python :: 3.12
Classifier: Programming Language :: Python :: 3.13
Classifier: Programming Language :: Python :: 3.14
Classifier: Programming Language :: Python :: Implementation :: CPython
Classifier: Programming Language :: Python :: Implementation :: PyPy
Requires-Python: >=3.8
Requires-Dist: brotli
Requires-Dist: python-dateutil
